peachpayments_partner/__init__.py
peachpayments_partner/authentication.py
peachpayments_partner/config.py
peachpayments_partner/error_response.py
peachpayments_partner/exceptions.py
peachpayments_partner/fixtures.py
peachpayments_partner/jwt_formatter.py
peachpayments_partner/result_codes.py
peachpayments_partner-0.1.14.dist-info/LICENSE.txt
peachpayments_partner-0.1.14.dist-info/METADATA
peachpayments_partner-0.1.14.dist-info/WHEEL
peachpayments_partner-0.1.14.dist-info/RECORD
