Metadata-Version: 2.3
Name: peachpayments-partner
Version: 0.1.14
Summary: PeachPayments Partner Library is a platform agnostic Python package to help integrating PeachPayments with their partners.
License: MIT
Author: PeachPayments
Author-email: support@peachpayments.com
Requires-Python: >=3.9,<4.0
Classifier: Development Status :: 4 - Beta
Classifier: Intended Audience :: Developers
Classifier: Intended Audience :: Financial and Insurance Industry
Classifier: License :: OSI Approved :: MIT License
Classifier: Operating System :: OS Independent
Classifier: Programming Language :: Python :: 3
Classifier: Programming Language :: Python :: 3.9
Classifier: Programming Language :: Python :: 3.10
Classifier: Programming Language :: Python :: 3.11
Classifier: Programming Language :: Python :: 3.12
Classifier: Programming Language :: Python :: 3.13
Classifier: Topic :: Software Development :: Libraries :: Python Modules
Classifier: Topic :: Utilities
Classifier: Typing :: Typed
Requires-Dist: PyJWT (>=2.4.0,<3.0.0)
Requires-Dist: iso4217 (>=1.9.20220401,<2.0.0)
Requires-Dist: requests (>=2.28.0,<3.0.0)
Project-URL: Repository, https://gitlab.com/peachpayments/peach-partner-python/
